itzam/__init__.py
itzam/base/__init__.py
itzam/base/client.py
itzam/models/__init__.py
itzam/models/__main__.py
itzam/models/client.py
itzam/models/models.py
itzam/objects/__init__.py
itzam/objects/client.py
itzam/objects/models.py
itzam/runs/__init__.py
itzam/runs/client.py
itzam/runs/models.py
itzam/text/__init__.py
itzam/text/client.py
itzam/text/models.py
itzam/threads/__init__.py
itzam/threads/client.py
itzam/threads/models.py
itzam/utils/exceptions.py
itzam/webhooks/models/__init__.py
itzam-1.2.0.dist-info/METADATA
itzam-1.2.0.dist-info/WHEEL
itzam-1.2.0.dist-info/top_level.txt
itzam-1.2.0.dist-info/RECORD
