Metadata-Version: 2.4
Name: itzam
Version: 1.2.0
Summary: Python SDK to interact with Itzam's API
Author-email: Joaquim Cassano <joaquim@cassano.com.br>
Requires-Python: <4.0,>=3.10
Requires-Dist: pydantic
Requires-Dist: requests
Requires-Dist: rich
